kroki/__init__.py
kroki/test.py
kroki-0.1.6.dist-info/LICENSE
kroki-0.1.6.dist-info/METADATA
kroki-0.1.6.dist-info/WHEEL
kroki-0.1.6.dist-info/top_level.txt
kroki-0.1.6.dist-info/RECORD
