Metadata-Version: 2.1
Name: kroki
Version: 0.1.6
Summary: Access kroki from python
Home-page: https://github.com/thorwhalen/kroki
Author: Thor Whalen
License: apache-2.0
Platform: any
License-File: LICENSE
Requires-Dist: i2
Requires-Dist: requests
Requires-Dist: IPython
